actuariat_python/__init__.py
actuariat_python/rss_teachings.xml
actuariat_python/automation/PythonActuariat.ico
actuariat_python/automation/R_install.r
actuariat_python/automation/__init__.py
actuariat_python/automation/notebook_test_helper.py
actuariat_python/data/__init__.py
actuariat_python/data/data_exceptions.py
actuariat_python/data/elections.py
actuariat_python/data/geocoding.py
actuariat_python/data/population.py
actuariat_python/data/wolf.py
actuariat_python/data/data_elections/__init__.py
actuariat_python/data/data_elections/cdsp_presi2012t1_circ.xls
actuariat_python/data/data_elections/cdsp_presi2012t2_circ.xls
actuariat_python/data/data_elections/villesgeo.zip
actuariat_python/data/data_population/TF00-02_D.xls
actuariat_python/data/data_population/TH00-02_D.xls
actuariat_python/data/data_population/__init__.py
actuariat_python/data/data_population/irsocsd2014_G10.xlsx
actuariat_python/data/data_population/pop-totale-france.xlsx
actuariat_python/exams/__init__.py
actuariat_python/exams/ex2016.py
actuariat_python/faq/__init__.py
actuariat_python/faq/faq_pandas.py
actuariat_python/faq/faq_python.py
actuariat_python/plots/__init__.py
actuariat_python/plots/pyramid.py
actuariat_python-0.5.659.dist-info/LICENSE.txt
actuariat_python-0.5.659.dist-info/METADATA
actuariat_python-0.5.659.dist-info/WHEEL
actuariat_python-0.5.659.dist-info/top_level.txt
actuariat_python-0.5.659.dist-info/RECORD
