Metadata-Version: 2.1
Name: actuariat-python
Version: 0.5.659
Summary: Helpers for teaching purposes (includes sqllite helpers)
Home-page: http://www.xavierdupre.fr/app/actuariat_python/helpsphinx/index.html
Author: Xavier Dupré
Author-email: xavier.dupre@gmail.com
License: MIT
Download-URL: https://github.com/sdpython/actuariat_python/
Keywords: actuariat_python,ENSAE,sqllite,database,teachings
Platform: UNKNOWN
Classifier: Programming Language :: Python :: 3
Classifier: Intended Audience :: Developers
Classifier: Topic :: Scientific/Engineering
Classifier: Topic :: Education
Classifier: License :: OSI Approved :: MIT License
Classifier: Development Status :: 5 - Production/Stable
Requires-Dist: pyquickhelper (>=1.10)
Requires-Dist: pyensae
Requires-Dist: pymyinstall
Requires-Dist: mlstatpy
Requires-Dist: scikit-learn
Requires-Dist: pyrsslocal
Requires-Dist: pandas
Requires-Dist: numpy
Requires-Dist: matplotlib
Requires-Dist: jupyter
